dec_bin_converter_Angileri_lorenzo/__init__.py
dec_bin_converter_Angileri_lorenzo/converter.py
TP_release_converter-0.0.2.dist-info/LICENSE
TP_release_converter-0.0.2.dist-info/METADATA
TP_release_converter-0.0.2.dist-info/WHEEL
TP_release_converter-0.0.2.dist-info/top_level.txt
TP_release_converter-0.0.2.dist-info/RECORD
