Metadata-Version: 2.1
Name: TP-release-converter
Version: 0.0.2
Summary: apprentissage de relaese de package
Author-email: Angileri <lorenzo.angileri@isen.yncrea.fr>
Classifier: Programming Language :: Python :: 3
Classifier: License :: OSI Approved :: MIT License
Classifier: Operating System :: OS Independent
Requires-Python: >=3.7
License-File: LICENSE
